{
    "_links": {
        "self": {
            "href": "http:\/\/default\/taxonomy\/term\/10?_format=hal_json"
        },
        "type": {
            "href": "http:\/\/drupal.org\/rest\/type\/taxonomy_term\/language"
        }
    },
    "tid": [
        {
            "value": 10
        }
    ],
    "uuid": [
        {
            "value": "b7d9b75f-a889-4746-889d-0f2e44072ed0"
        }
    ],
    "langcode": [
        {
            "value": "en",
            "lang": "en"
        }
    ],
    "vid": [
        {
            "target_id": "language"
        }
    ],
    "name": [
        {
            "value": "English",
            "lang": "en"
        }
    ],
    "weight": [
        {
            "value": 0
        }
    ],
    "changed": [
        {
            "value": "2018-06-22T21:10:53+00:00",
            "lang": "en",
            "format": "Y-m-d\\TH:i:sP"
        }
    ],
    "default_langcode": [
        {
            "value": true,
            "lang": "en"
        }
    ],
    "metatag": [
        {
            "value": {
                "title": "English | My Drupal 8 Site",
                "canonical_url": "http:\/\/default\/taxonomy\/term\/10"
            }
        }
    ],
    "status": [
        {
            "value": true,
            "lang": "en"
        }
    ]
}